gerapy/__init__.py
gerapy/__version__.py
gerapy/settings.py
gerapy/cmd/__init__.py
gerapy/cmd/generate.py
gerapy/cmd/init.py
gerapy/cmd/initadmin.py
gerapy/cmd/parse.py
gerapy/downloadermiddlewares/__init__.py
gerapy/downloadermiddlewares/cookies.py
gerapy/downloadermiddlewares/proxy.py
gerapy/downloadermiddlewares/pyppeteer.py
gerapy/pipelines/__init__.py
gerapy/pipelines/mongodb.py
gerapy/pipelines/mysql.py
gerapy/server/__init__.py
gerapy/server/manage.py
gerapy/server/core/__init__.py
gerapy/server/core/admin.py
gerapy/server/core/apps.py
gerapy/server/core/build.py
gerapy/server/core/config.py
gerapy/server/core/encoder.py
gerapy/server/core/middlewares.py
gerapy/server/core/models.py
gerapy/server/core/parser.py
gerapy/server/core/response.py
gerapy/server/core/scheduler.py
gerapy/server/core/tests.py
gerapy/server/core/time.py
gerapy/server/core/urls.py
gerapy/server/core/utils.py
gerapy/server/core/views.py
gerapy/server/core/migrations/0001_initial.py
gerapy/server/core/migrations/0002_auto_20180119_1210.py
gerapy/server/core/migrations/0003_auto_20180123_2304.py
gerapy/server/core/migrations/0004_auto_20180124_0032.py
gerapy/server/core/migrations/0005_auto_20180131_1210.py
gerapy/server/core/migrations/0006_auto_20180131_1235.py
gerapy/server/core/migrations/0007_task_trigger.py
gerapy/server/core/migrations/0008_auto_20180703_2305.py
gerapy/server/core/migrations/0009_auto_20180711_2332.py
gerapy/server/core/migrations/0010_auto_20191027_2040.py
gerapy/server/core/migrations/__init__.py
gerapy/server/core/templates/favicon.ico
gerapy/server/core/templates/index.html
gerapy/server/core/templates/static/css/app.6008ee66.css
gerapy/server/core/templates/static/css/app.6008ee66.css.map
gerapy/server/core/templates/static/css/app.e8b12703.css
gerapy/server/core/templates/static/css/app.e8b12703.css.map
gerapy/server/core/templates/static/css/chunk-10b2edc2.79f68610.css
gerapy/server/core/templates/static/css/chunk-10b2edc2.79f68610.css.map
gerapy-0.9.11.dist-info/LICENSE
gerapy-0.9.11.dist-info/METADATA
gerapy-0.9.11.dist-info/WHEEL
gerapy-0.9.11.dist-info/entry_points.txt
gerapy-0.9.11.dist-info/top_level.txt
gerapy-0.9.11.dist-info/RECORD
