Metadata-Version: 2.1
Name: gerapy
Version: 0.9.11
Summary: Distributed Crawler Management Framework Based on Scrapy, Scrapyd, Scrapyd-Client, Scrapyd-API, Django and Vue.js
Home-page: https://github.com/Gerapy/Gerapy
Author: Germey
Author-email: cqc@cuiqingcai.com
License: MIT
Platform: UNKNOWN
Classifier: License :: OSI Approved :: MIT License
Classifier: Programming Language :: Python :: 3.5
Classifier: Programming Language :: Python :: 3.6
Classifier: Programming Language :: Python :: 3.7
Classifier: Programming Language :: Python :: 3.8
Classifier: Programming Language :: Python :: 3.9
Classifier: Programming Language :: Python :: Implementation :: CPython
Classifier: Programming Language :: Python :: Implementation :: PyPy
Requires-Python: >=3.5.0
License-File: LICENSE
Requires-Dist: apscheduler (<=3.7.0,>=3.5.1)
Requires-Dist: cryptography (>=2.8)
Requires-Dist: django (<3.0,>=2.2)
Requires-Dist: django-cors-headers (<=3.7.0,>=3.2.0)
Requires-Dist: django-apscheduler (<=0.6.0,>=0.3.0)
Requires-Dist: furl (>=2.1.0)
Requires-Dist: jinja2 (>=2.11.3)
Requires-Dist: scrapy (>=2.0.0)
Requires-Dist: scrapy-redis (>=0.6.8)
Requires-Dist: scrapy-splash (>=0.7.2)
Requires-Dist: python-scrapyd-api (>=2.1.2)
Requires-Dist: redis (>=2.10.5)
Requires-Dist: requests (>=2.20.0)
Requires-Dist: pymongo (>=3.9.0)
Requires-Dist: pymysql (>=0.7.10)
Requires-Dist: pyquery (>=1.2.17)
Requires-Dist: beautifulsoup4 (>=4.7.0)
Requires-Dist: djangorestframework (>=3.11.2)
Requires-Dist: websocket (>=0.2.1)
Requires-Dist: pyppeteer (>=0.0.25)
